{
    "internal" :
    [
        {
            "subject":"<<Question||Meeting Info||Quick Question||Ayuda me!>>",
            "body": "What time is the <<staff||production||team||hr||marketing||finance||annual>> meeting?"
        },
        {
            "subject":"<<Your Performance||An Observation||Just Saying>>",
            "body": "I am <<really||very||quite||somewhat||especially>> <<happy with||disappointed with||sad about||confused about||content with|| ambivalent about>> your <<performance on||contribution to||opinion of>> the <<Henderson||Michaelson||Strongfellow||Samuelson||Flaherty>> <<account||report||sale||analysis>>."
        },
        {
            "subject":"<<Mega Millions||Powerball||Superbowl||World Series||Oscar>> Pool",
            "body": "Last call to participate in the <<Mega Millions||Powerball||Superbowl||World Series||Oscar>> Pool, <<stop by my desk||swing by customer service||pop by the mail room>> by <<end of business||lunch time||lights out>> <<today||tomorrow||friday>>."
        },
        {
            "subject":"<<Thanks||I appreciate||Totally cool||I owe you one>>",
            "body": "nm"
        },
        {
            "subject":"<<Sorry||Hey||About today||About tomorrow||About Later>>",
            "body": "Can we <<reschedule||try again||brainstorm||workshop some ideas>>?"
        },
        {
            "subject":"Re:<<Question||A little help||Can I get a few minutes of your time>>?",
            "body": "<<You are welcome||You're welcome||No problem||My pleasure||Don't be silly, I was happy to help||No, thank YOU>>"
        }
        
    ],

    "external" :
    [
        {
            "subject":"<<Hey You||My Dude||Long time||Reaching out>>",
            "body": "<<Hey||Wassup||Hi>>, it's Pam, from <<Freemont High||Banneker SHS||Coconut Grove Elementary||West Lab||Fort Lincoln>>. You probably don't remember me, but we are planning our reunion for next summer and wanted to see if you would be attending?"
        },
        {
            "subject":"Your Enterprise <<Backup Strategy||Hardware Refresh||Technical Training||student loan debt>>",
            "body": "I am <<really||very||quite||somewhat||especially>> <<happy||excited||proud>> to share <<an opportunity||a secret||my plan>> to help your to deal with your <<car insurance||extended warranty||life insurance||student loan debt>>."
        },
        {
            "subject":"Your <<car insurance||extended warranty||life insurance||student loan debt>>",
            "body": "I am <<really||very||quite||somewhat||especially>> <<happy||excited||proud>> to share <<an opportunity||a secret||my plan>> to help your to deal with your <<car insurance||extended warranty||life insurance||student loan debt>>."
        }
    ],
    "malware" :
    [
        {
            "subject":"Password Check Required Immediately",
            "body": "Your account has been flagged, please verify your email with the link below"
        },
        {
            "subject":"A Delivery Attempt was made",
            "body": "A <<DHL||UPS||FedEx||USPS||Global Freight>> delivery was not able to reach you. Please click the link below to reschedule delivery."
        },
        {
            "subject":"<<Microsoft||Apple||iTunes||Google>> account recovery message",
            "body": "In order to reset the password on your <<Microsoft||Apple||iTunes||Google>> account, you need to click the following link."
        },
        {
            "subject":"A new deal in the <<Microsoft||Apple||Amazon>> store",
            "body": "You have been selected to save 75% on your next <<Microsoft||Apple||Amazon>> purchase. Click below to claim your coupon."
        },
        {
            "subject":"New login from suspicious location",
            "body": "There was a login to your <<Yahoo||Gmail||Hotmail||Outlook||Comcast||AOL>> account from a suspicious location. See below for details."
        },
        {
            "subject":"XBOX or PS4",
            "body": "Clearly the choice of the discerning gamer is the <<XBOX||PS4>>. To join the exclusive <<XBOX||PS4>> discount club, complete the following registration."
        }
    ]
}
